README.rst
setup.py
/home/yan/crypyto/crypyto/static/Betamaze/0.png
/home/yan/crypyto/crypyto/static/Betamaze/1.png
/home/yan/crypyto/crypyto/static/Betamaze/2.png
/home/yan/crypyto/crypyto/static/Betamaze/3.png
/home/yan/crypyto/crypyto/static/Betamaze/4.png
/home/yan/crypyto/crypyto/static/Betamaze/5.png
/home/yan/crypyto/crypyto/static/Betamaze/6.png
/home/yan/crypyto/crypyto/static/Betamaze/7.png
/home/yan/crypyto/crypyto/static/Betamaze/8.png
/home/yan/crypyto/crypyto/static/Betamaze/9.png
/home/yan/crypyto/crypyto/static/Betamaze/A.png
/home/yan/crypyto/crypyto/static/Betamaze/B.png
/home/yan/crypyto/crypyto/static/Betamaze/C.png
/home/yan/crypyto/crypyto/static/Betamaze/D.png
/home/yan/crypyto/crypyto/static/Betamaze/E.png
/home/yan/crypyto/crypyto/static/Betamaze/F.png
/home/yan/crypyto/crypyto/static/Betamaze/G.png
/home/yan/crypyto/crypyto/static/Betamaze/H.png
/home/yan/crypyto/crypyto/static/Betamaze/I.png
/home/yan/crypyto/crypyto/static/Betamaze/J.png
/home/yan/crypyto/crypyto/static/Betamaze/K.png
/home/yan/crypyto/crypyto/static/Betamaze/L.png
/home/yan/crypyto/crypyto/static/Betamaze/M.png
/home/yan/crypyto/crypyto/static/Betamaze/N.png
/home/yan/crypyto/crypyto/static/Betamaze/O.png
/home/yan/crypyto/crypyto/static/Betamaze/P.png
/home/yan/crypyto/crypyto/static/Betamaze/Q.png
/home/yan/crypyto/crypyto/static/Betamaze/R.png
/home/yan/crypyto/crypyto/static/Betamaze/S.png
/home/yan/crypyto/crypyto/static/Betamaze/T.png
/home/yan/crypyto/crypyto/static/Betamaze/U.png
/home/yan/crypyto/crypyto/static/Betamaze/V.png
/home/yan/crypyto/crypyto/static/Betamaze/W.png
/home/yan/crypyto/crypyto/static/Betamaze/X.png
/home/yan/crypyto/crypyto/static/Betamaze/Y.png
/home/yan/crypyto/crypyto/static/Betamaze/Z.png
/home/yan/crypyto/crypyto/static/Betamaze/colon.png
/home/yan/crypyto/crypyto/static/Betamaze/comma.png
/home/yan/crypyto/crypyto/static/Betamaze/parenthesis.png
/home/yan/crypyto/crypyto/static/Betamaze/period.png
crypyto.egg-info/PKG-INFO
crypyto.egg-info/SOURCES.txt
crypyto.egg-info/dependency_links.txt
crypyto.egg-info/requires.txt
crypyto.egg-info/top_level.txt
