Metadata-Version: 1.1
Name: crypyto
Version: 0.3.0
Summary: crypyto is a Python package that provides simple usage of cryptography tools and ciphers on your programs.
Home-page: https://github.com/yanorestes/crypyto
Author: Yan Orestes
Author-email: yan.orestes@alura.com.br
License: MIT
Download-URL: https://github.com/yanorestes/crypyto/archive/0.3.0.zip
Keywords: crypto cryptography cipher
Platform: UNKNOWN
Classifier: Development Status :: 3 - Alpha
Classifier: Environment :: Console
Classifier: Intended Audience :: Developers
Classifier: Intended Audience :: Education
Classifier: License :: OSI Approved :: MIT License
Classifier: Natural Language :: English
Classifier: Operating System :: OS Independent
Classifier: Programming Language :: Python :: 3
Classifier: Programming Language :: Python :: 3.5
Classifier: Programming Language :: Python :: 3.6
Classifier: Programming Language :: Python :: 3.7
Classifier: Topic :: Security :: Cryptography
